target_azure_storage/__init__.py
target_azure_storage/sinks.py
target_azure_storage/target.py
target_azure_storage/tests/__init__.py
target_azure_storage/tests/test_core.py
target_azure_storage-0.0.1.dist-info/entry_points.txt
target_azure_storage-0.0.1.dist-info/WHEEL
target_azure_storage-0.0.1.dist-info/METADATA
target_azure_storage-0.0.1.dist-info/RECORD
