Metadata-Version: 2.1
Name: target-azure-storage
Version: 0.0.1
Summary: `target-azure-storage` is a Singer target for Azure Storage, built with the Meltano SDK for Singer Targets.
License: Apache 2.0
Keywords: meltano,singer,azure,storage
Author: Jules Huisman
Requires-Python: >=3.8,<3.11
Classifier: License :: Other/Proprietary License
Classifier: Programming Language :: Python :: 3
Classifier: Programming Language :: Python :: 3.10
Classifier: Programming Language :: Python :: 3.8
Classifier: Programming Language :: Python :: 3.9
Requires-Dist: adlfs (>=2022.2.0,<2023.0.0)
Requires-Dist: azure-storage-file-datalake (>=12.5.0,<13.0.0)
Requires-Dist: fsspec (>=2022.1.0,<2023.0.0)
Requires-Dist: pandas (>=1.4.1,<2.0.0)
Requires-Dist: pyarrow (>=7.0.0,<8.0.0)
Requires-Dist: requests (>=2.25.1,<3.0.0)
Requires-Dist: singer-sdk (>=0.4.3,<0.5.0)
